textscore/__init__.py
textscore/constants.py
textscore/factory.py
textscore/scorer.py
textscore/sequencer.py
textscore/strategy.py
textscore/types.py
textscore-0.1.0.dist-info/LICENSE
textscore-0.1.0.dist-info/WHEEL
textscore-0.1.0.dist-info/METADATA
textscore-0.1.0.dist-info/RECORD
