Metadata-Version: 2.1
Name: textscore
Version: 0.1.0
Summary: Tool for assesing the quality of text using causal LM.
License: MIT
Author: Alex Varga
Author-email: alex@hylix.co
Requires-Python: >=3.10,<4.0
Classifier: License :: OSI Approved :: MIT License
Classifier: Programming Language :: Python :: 3
Classifier: Programming Language :: Python :: 3.10
Classifier: Programming Language :: Python :: 3.11
Requires-Dist: torch (>=1.13.1,<2.0.0)
Requires-Dist: transformers (>=4.25.1,<5.0.0)
